LICENSE
README.md
setup.py
pr2up_py/__init__.py
pr2up_py/pr2up.py
pr2up_py.egg-info/PKG-INFO
pr2up_py.egg-info/SOURCES.txt
pr2up_py.egg-info/dependency_links.txt
pr2up_py.egg-info/requires.txt
pr2up_py.egg-info/top_level.txt