Metadata-Version: 2.1
Name: pr2up-py
Version: 0.1
Summary: API pr2up.com
Home-page: https://github.com/scvgde/pr2up_api
Author: GFNPRO
Author-email: blxcksxvxgesmile@gmail.com
License: UNKNOWN
Platform: UNKNOWN
Classifier: Programming Language :: Python :: 3.9
Classifier: License :: OSI Approved :: GNU General Public License v3 (GPLv3)
License-File: LICENSE
